odoo/addons/shipment_advice_bill_auto_complete/README.rst
odoo/addons/shipment_advice_bill_auto_complete/__init__.py
odoo/addons/shipment_advice_bill_auto_complete/__manifest__.py
odoo/addons/shipment_advice_bill_auto_complete/i18n/shipment_advice_bill_auto_complete.pot
odoo/addons/shipment_advice_bill_auto_complete/models/__init__.py
odoo/addons/shipment_advice_bill_auto_complete/models/account_move.py
odoo/addons/shipment_advice_bill_auto_complete/models/account_move_line.py
odoo/addons/shipment_advice_bill_auto_complete/models/shipment_advice.py
odoo/addons/shipment_advice_bill_auto_complete/models/stock_move.py
odoo/addons/shipment_advice_bill_auto_complete/readme/CONTRIBUTORS.rst
odoo/addons/shipment_advice_bill_auto_complete/readme/DESCRIPTION.rst
odoo/addons/shipment_advice_bill_auto_complete/readme/USAGE.rst
odoo/addons/shipment_advice_bill_auto_complete/static/description/icon.png
odoo/addons/shipment_advice_bill_auto_complete/static/description/index.html
odoo/addons/shipment_advice_bill_auto_complete/tests/__init__.py
odoo/addons/shipment_advice_bill_auto_complete/tests/test_shipment_advice_bill_auto_complete.py
odoo/addons/shipment_advice_bill_auto_complete/views/account_move_views.xml
odoo14_addon_shipment_advice_bill_auto_complete-14.0.1.3.0.dist-info/METADATA
odoo14_addon_shipment_advice_bill_auto_complete-14.0.1.3.0.dist-info/WHEEL
odoo14_addon_shipment_advice_bill_auto_complete-14.0.1.3.0.dist-info/top_level.txt
odoo14_addon_shipment_advice_bill_auto_complete-14.0.1.3.0.dist-info/RECORD
